quart_admin/__init__.py
quart_admin/cli.py
quart_admin/contents.py
quart_admin/context.py
quart_admin/helpers.py
quart_admin-3.0.0.dist-info/LICENSE
quart_admin-3.0.0.dist-info/METADATA
quart_admin-3.0.0.dist-info/WHEEL
quart_admin-3.0.0.dist-info/entry_points.txt
quart_admin-3.0.0.dist-info/top_level.txt
quart_admin-3.0.0.dist-info/RECORD
